rbaca/__init__.py
rbaca/admin.py
rbaca/api/__init__.py
rbaca/api/serializers.py
rbaca/api/utils.py
rbaca/api/views.py
rbaca/apps.py
rbaca/backends.py
rbaca/decorators.py
rbaca/forms.py
rbaca/migrations/0001_initial.py
rbaca/migrations/0002_roleexpiration_uuid.py
rbaca/migrations/__init__.py
rbaca/mixins.py
rbaca/models.py
rbaca/templates/rbaca/role_confirm_delete.html
rbaca/templates/rbaca/role_detail.html
rbaca/templates/rbaca/role_form.html
rbaca/templates/rbaca/role_list.html
rbaca/templatetags/__init__.py
rbaca/templatetags/rbaca_tags.py
rbaca/urls.py
rbaca/views.py
django_rbaca-1.1.1.dist-info/LICENSE.md
django_rbaca-1.1.1.dist-info/METADATA
django_rbaca-1.1.1.dist-info/WHEEL
django_rbaca-1.1.1.dist-info/RECORD
