Metadata-Version: 2.1
Name: django-rbaca
Version: 1.1.1
Summary: Role-based access control with attributes for Django
Author: Steven Bruch
Requires-Python: >=3.9,<4.0
Classifier: Programming Language :: Python :: 3
Classifier: Programming Language :: Python :: 3.9
Classifier: Programming Language :: Python :: 3.10
Classifier: Programming Language :: Python :: 3.11
Classifier: Programming Language :: Python :: 3.12
Classifier: Programming Language :: Python :: 3.13
Requires-Dist: django (>=4.2.17,<5.0.0)
Requires-Dist: djangorestframework (>=3.15.1,<4.0.0)
Requires-Dist: drf-jwt (>=1.19.2,<2.0.0)
Requires-Dist: sphinx (>=7.3.7,<8.0.0)
Requires-Dist: sphinx-rtd-theme (>=1.3.0,<2.0.0)
